pyworks_storage/aws.py
pyworks_storage/config.py
pyworks_storage/interfaces.py
pyworks_storage/storage.py
pyworks_storage-0.1.0a2.dist-info/LICENSE
pyworks_storage-0.1.0a2.dist-info/WHEEL
pyworks_storage-0.1.0a2.dist-info/METADATA
pyworks_storage-0.1.0a2.dist-info/RECORD
