Metadata-Version: 2.1
Name: pyworks-storage
Version: 0.1.0a2
Summary: Provide a variety of storage backends in a single library.
Home-page: https://github.com/pyworksasia/pyworks-storage
License: MIT
Keywords: packaging,poetry
Author: PyWorks Asia Team
Author-email: opensource@pyworks.asia
Requires-Python: >=3.7,<4.0
Classifier: License :: OSI Approved :: MIT License
Classifier: Programming Language :: Python :: 3
Classifier: Programming Language :: Python :: 3.7
Classifier: Programming Language :: Python :: 3.8
Classifier: Programming Language :: Python :: 3.9
Requires-Dist: boto3 (>=1.17.24,<2.0.0)
Requires-Dist: python-dotenv (>=0.15.0,<0.16.0)
Project-URL: Repository, https://github.com/pyworksasia/pyworks-storage
